[ {
  "text" : "Time allocation",
  "anchor" : "para28"
}, {
  "text" : "Legislative pages",
  "anchor" : "para317"
}, {
  "text" : "Health care funding",
  "anchor" : "para322"
}, {
  "text" : "Health care funding",
  "anchor" : "para374"
}, {
  "text" : "Privatization of public assets",
  "anchor" : "para415"
}, {
  "text" : "Privatization of public assets",
  "anchor" : "para438"
}, {
  "text" : "Health care",
  "anchor" : "para468"
}, {
  "text" : "Health care funding",
  "anchor" : "para487"
}, {
  "text" : "Elder abuse",
  "anchor" : "para507"
}, {
  "text" : "Health care funding",
  "anchor" : "para523"
}, {
  "text" : "Teachers’ collective bargaining",
  "anchor" : "para542"
}, {
  "text" : "Renewable energy",
  "anchor" : "para562"
}, {
  "text" : "Teachers’ collective bargaining",
  "anchor" : "para581"
}, {
  "text" : "Manufacturing jobs",
  "anchor" : "para600"
}, {
  "text" : "Accessibility for the disabled",
  "anchor" : "para618"
}, {
  "text" : "Highway safety",
  "anchor" : "para631"
}, {
  "text" : "Correction of record",
  "anchor" : "para638"
}, {
  "text" : "Visitor",
  "anchor" : "para643"
}, {
  "text" : "Invasive Species Act, 2015 / Loi de 2015 sur les espèces envahissantes",
  "anchor" : "para648"
}, {
  "text" : "Highway safety",
  "anchor" : "para764"
}, {
  "text" : "Manufacturing jobs",
  "anchor" : "para769"
}, {
  "text" : "Optometry services",
  "anchor" : "para774"
}, {
  "text" : "Health care funding",
  "anchor" : "para778"
}, {
  "text" : "Community Health and Wellbeing Week",
  "anchor" : "para783"
}, {
  "text" : "Concussion",
  "anchor" : "para788"
}, {
  "text" : "Taxation",
  "anchor" : "para794"
}, {
  "text" : "Automated vehicles",
  "anchor" : "para799"
}, {
  "text" : "Bowmanville Hospital Foundation",
  "anchor" : "para806"
}, {
  "text" : "Standing Committee on Regulations and Private Bills",
  "anchor" : "para811"
}, {
  "text" : "Women’s History Month / Mois de l’histoire des femmes",
  "anchor" : "para820"
}, {
  "text" : "Waste Reduction Week",
  "anchor" : "para835"
}, {
  "text" : "Women’s History Month",
  "anchor" : "para850"
}, {
  "text" : "Waste Reduction Week",
  "anchor" : "para858"
}, {
  "text" : "Women’s History Month",
  "anchor" : "para868"
}, {
  "text" : "Waste Reduction Week",
  "anchor" : "para875"
}, {
  "text" : "Concussion",
  "anchor" : "para882"
}, {
  "text" : "Privatization of public assets",
  "anchor" : "para893"
}, {
  "text" : "Student safety",
  "anchor" : "para902"
}, {
  "text" : "Hydro rates",
  "anchor" : "para911"
}, {
  "text" : "Information technology services",
  "anchor" : "para920"
}, {
  "text" : "Water fluoridation",
  "anchor" : "para928"
}, {
  "text" : "Ontario farmers",
  "anchor" : "para938"
}, {
  "text" : "Diagnostic services",
  "anchor" : "para945"
}, {
  "text" : "Lung health",
  "anchor" : "para952"
}, {
  "text" : "Renewable energy",
  "anchor" : "para960"
}, {
  "text" : "Long-term care",
  "anchor" : "para968"
}, {
  "text" : "Public transit",
  "anchor" : "para978"
}, {
  "text" : "Ontario farmers",
  "anchor" : "para987"
}, {
  "text" : "Health care funding",
  "anchor" : "para995"
} ]