[ {
  "text" : "Members’ expenditures",
  "anchor" : "para27"
}, {
  "text" : "Smoke-Free Ontario Amendment Act, 2016 / Loi de 2016 modifiant la Loi favorisant un Ontario sans fumée",
  "anchor" : "para30"
}, {
  "text" : "Special report, Auditor General",
  "anchor" : "para194"
}, {
  "text" : "Order of business",
  "anchor" : "para219"
}, {
  "text" : "Visitors",
  "anchor" : "para230"
}, {
  "text" : "Clifford Pilkey",
  "anchor" : "para236"
}, {
  "text" : "Energy policies",
  "anchor" : "para290"
}, {
  "text" : "School facilities",
  "anchor" : "para329"
}, {
  "text" : "Mercury poisoning",
  "anchor" : "para357"
}, {
  "text" : "Hospital funding",
  "anchor" : "para377"
}, {
  "text" : "Pan Am Games",
  "anchor" : "para412"
}, {
  "text" : "Climate change",
  "anchor" : "para436"
}, {
  "text" : "Mining industry",
  "anchor" : "para455"
}, {
  "text" : "Special-needs students",
  "anchor" : "para471"
}, {
  "text" : "Pan Am Games",
  "anchor" : "para486"
}, {
  "text" : "Sexual violence and harassment",
  "anchor" : "para510"
}, {
  "text" : "Transportation infrastructure",
  "anchor" : "para529"
}, {
  "text" : "Education funding",
  "anchor" : "para545"
}, {
  "text" : "Seniors",
  "anchor" : "para563"
}, {
  "text" : "Anti-Semitism",
  "anchor" : "para584"
}, {
  "text" : "Impact! Youth Summit",
  "anchor" : "para605"
}, {
  "text" : "Commemoration of fallen soldiers",
  "anchor" : "para614"
}, {
  "text" : "Attorney General’s Victim Services Awards of Distinction",
  "anchor" : "para620"
}, {
  "text" : "Events in Huron–Bruce",
  "anchor" : "para626"
}, {
  "text" : "Brampton kabaddi tournament",
  "anchor" : "para636"
}, {
  "text" : "Ontario Volunteer Service Awards / Distinctions de l’Ontario pour services bénévoles",
  "anchor" : "para643"
}, {
  "text" : "Environmental protection",
  "anchor" : "para650"
}, {
  "text" : "St. John Chrysostom Catholic Church",
  "anchor" : "para657"
}, {
  "text" : "Bike Month",
  "anchor" : "para665"
}, {
  "text" : "Standing Committee on Regulations and Private Bills",
  "anchor" : "para674"
}, {
  "text" : "Education Amendment Act (Regional Aboriginal School Boards), 2016 / Loi de 2016 modifiant la Loi sur l’éducation (conseils scolaires autochtones régionaux)",
  "anchor" : "para681"
}, {
  "text" : "Hazel McCallion Day Act, 2016 / Loi de 2016 sur le Jour de Hazel McCallion",
  "anchor" : "para688"
}, {
  "text" : "Greater Access to Hepatitis C Treatment Act, 2016 / Loi de 2016 sur l’élargissement de l’accès au traitement de l’hépatite C",
  "anchor" : "para696"
}, {
  "text" : "Service Dogs for Persons with Disabilities Act, 2016 / Loi de 2016 sur les chiens d’assistance pour les personnes handicapées",
  "anchor" : "para708"
}, {
  "text" : "Burden Reduction Act, 2016 / Loi de 2016 sur l’allègement du fardeau réglementaire",
  "anchor" : "para720"
}, {
  "text" : "House sittings",
  "anchor" : "para729"
}, {
  "text" : "Local Food Week / Semaine des aliments locaux",
  "anchor" : "para744"
}, {
  "text" : "Autism treatment",
  "anchor" : "para785"
}, {
  "text" : "Post-secondary sector employees",
  "anchor" : "para794"
}, {
  "text" : "Speed limits",
  "anchor" : "para804"
}, {
  "text" : "Health care funding",
  "anchor" : "para812"
}, {
  "text" : "Services for the developmentally disabled",
  "anchor" : "para820"
}, {
  "text" : "Blood donation",
  "anchor" : "para835"
}, {
  "text" : "Health care funding",
  "anchor" : "para843"
}, {
  "text" : "Health care",
  "anchor" : "para851"
}, {
  "text" : "Climate change",
  "anchor" : "para861"
}, {
  "text" : "Health care funding",
  "anchor" : "para872"
}, {
  "text" : "Dental care",
  "anchor" : "para880"
}, {
  "text" : "Housing Services Corp.",
  "anchor" : "para890"
}, {
  "text" : "Privatization of public assets",
  "anchor" : "para901"
}, {
  "text" : "Order of business",
  "anchor" : "para913"
}, {
  "text" : "Correctional Services Staff Recognition Week Act, 2016 / Loi de 2016 sur la Semaine de la reconnaissance du personnel des services correctionnels",
  "anchor" : "para934"
}, {
  "text" : "Correctional Services Staff Recognition Week Act, 2016 / Loi de 2016 sur la Semaine de la reconnaissance du personnel des services correctionnels",
  "anchor" : "para939"
}, {
  "text" : "Workers Day of Mourning Act, 2016 / Loi de 2016 sur le Jour de deuil pour les travailleurs",
  "anchor" : "para945"
}, {
  "text" : "Order of business",
  "anchor" : "para1112"
}, {
  "text" : "Association of Municipal Managers, Clerks and Treasurers of Ontario Act, 2016",
  "anchor" : "para1122"
}, {
  "text" : "Association of Municipal Managers, Clerks and Treasurers of Ontario Act, 2016",
  "anchor" : "para1128"
}, {
  "text" : "Stephanie Holdings Ltd. Act, 2016",
  "anchor" : "para1134"
}, {
  "text" : "Stephanie Holdings Ltd. Act, 2016",
  "anchor" : "para1139"
}, {
  "text" : "Bill Bedford Professional Corporation Act, 2016",
  "anchor" : "para1145"
}, {
  "text" : "Bill Bedford Professional Corporation Act, 2016",
  "anchor" : "para1150"
}, {
  "text" : "1709542 Ontario Corporation Act, 2016",
  "anchor" : "para1156"
}, {
  "text" : "1709542 Ontario Corporation Act, 2016",
  "anchor" : "para1161"
}, {
  "text" : "839255 Ontario Inc. Act, 2016",
  "anchor" : "para1167"
}, {
  "text" : "839255 Ontario Inc. Act, 2016",
  "anchor" : "para1172"
}, {
  "text" : "Base2 eBusiness Solutions Inc. Act, 2016",
  "anchor" : "para1178"
}, {
  "text" : "Base2 eBusiness Solutions Inc. Act, 2016",
  "anchor" : "para1183"
}, {
  "text" : "Corporation of Massey Hall and Roy Thomson Hall Act (Tax Relief), 2016",
  "anchor" : "para1189"
}, {
  "text" : "Corporation of Massey Hall and Roy Thomson Hall Act (Tax Relief), 2016",
  "anchor" : "para1194"
}, {
  "text" : "828117 Ontario Limited Act, 2016",
  "anchor" : "para1200"
}, {
  "text" : "828117 Ontario Limited Act, 2016",
  "anchor" : "para1205"
}, {
  "text" : "Bud Monahan Guitar Sales & Service Ltd. Act, 2016",
  "anchor" : "para1211"
}, {
  "text" : "Bud Monahan Guitar Sales & Service Ltd. Act, 2016",
  "anchor" : "para1216"
}, {
  "text" : "790186 Ontario Inc. Act, 2016",
  "anchor" : "para1222"
}, {
  "text" : "790186 Ontario Inc. Act, 2016",
  "anchor" : "para1227"
}, {
  "text" : "Ismaili Centre, Toronto, Aga Khan Museum and Aga Khan Park Act (Tax Relief), 2016",
  "anchor" : "para1234"
}, {
  "text" : "Ismaili Centre, Toronto, Aga Khan Museum and Aga Khan Park Act (Tax Relief), 2016",
  "anchor" : "para1239"
}, {
  "text" : "1733387 Ontario Corp. Act, 2016",
  "anchor" : "para1245"
}, {
  "text" : "1733387 Ontario Corp. Act, 2016",
  "anchor" : "para1250"
}, {
  "text" : "Boys and Girls Club of Niagara Act (Tax Relief), 2016",
  "anchor" : "para1256"
}, {
  "text" : "Boys and Girls Club of Niagara Act (Tax Relief), 2016",
  "anchor" : "para1261"
}, {
  "text" : "Harold Coles Inc. Act, 2016",
  "anchor" : "para1267"
}, {
  "text" : "Harold Coles Inc. Act, 2016",
  "anchor" : "para1272"
}, {
  "text" : "Infectious disease control",
  "anchor" : "para1280"
}, {
  "text" : "Hospital funding",
  "anchor" : "para1304"
} ]