[ {
  "text" : "Burden Reduction Act, 2016 / Loi de 2016 sur l’allègement du fardeau réglementaire",
  "anchor" : "para187"
}, {
  "text" : "Energy policies",
  "anchor" : "para381"
}, {
  "text" : "Special-needs students",
  "anchor" : "para419"
}, {
  "text" : "Privatization of public assets",
  "anchor" : "para467"
}, {
  "text" : "Minimum wage",
  "anchor" : "para493"
}, {
  "text" : "Fiscal accountability",
  "anchor" : "para517"
}, {
  "text" : "Fiscal accountability",
  "anchor" : "para537"
}, {
  "text" : "Employment standards",
  "anchor" : "para550"
}, {
  "text" : "Ontario Lottery and Gaming Corp.",
  "anchor" : "para562"
}, {
  "text" : "Poverty",
  "anchor" : "para577"
}, {
  "text" : "Ontario Municipal Board",
  "anchor" : "para591"
}, {
  "text" : "Road safety",
  "anchor" : "para604"
}, {
  "text" : "Hydro rates",
  "anchor" : "para615"
}, {
  "text" : "Impaired drivers",
  "anchor" : "para634"
}, {
  "text" : "Access to justice",
  "anchor" : "para649"
}, {
  "text" : "Visitor",
  "anchor" : "para662"
}, {
  "text" : "Hydro rates",
  "anchor" : "para672"
}, {
  "text" : "Joe Fiorito",
  "anchor" : "para676"
}, {
  "text" : "Events in Northumberland–Quinte West",
  "anchor" : "para679"
}, {
  "text" : "Paul Grein",
  "anchor" : "para686"
}, {
  "text" : "Disaster relief",
  "anchor" : "para707"
}, {
  "text" : "Kidney Walk",
  "anchor" : "para721"
}, {
  "text" : "Nuclear industry",
  "anchor" : "para728"
}, {
  "text" : "Student housing",
  "anchor" : "para736"
}, {
  "text" : "Canadian Cancer Survivor Network",
  "anchor" : "para743"
}, {
  "text" : "Visitors",
  "anchor" : "para749"
}, {
  "text" : "Albanian Heritage Month Act, 2016 / Loi de 2016 sur le Mois du patrimoine albanais",
  "anchor" : "para755"
}, {
  "text" : "Protecting Students Act, 2016 / Loi de 2016 protégeant les élèves",
  "anchor" : "para762"
}, {
  "text" : "Islamic Heritage Month Act, 2016 / Loi de 2016 sur le Mois du patrimoine musulman",
  "anchor" : "para778"
}, {
  "text" : "Ontario Agriculture Week",
  "anchor" : "para787"
}, {
  "text" : "World Teachers’ Day",
  "anchor" : "para817"
}, {
  "text" : "Ontario Agriculture Week",
  "anchor" : "para833"
}, {
  "text" : "World Teachers’ Day",
  "anchor" : "para839"
}, {
  "text" : "Ontario Agriculture Week",
  "anchor" : "para845"
}, {
  "text" : "World Teachers’ Day",
  "anchor" : "para851"
}, {
  "text" : "Automobile insurance",
  "anchor" : "para860"
}, {
  "text" : "Diabetes glucose monitoring",
  "anchor" : "para868"
}, {
  "text" : "Privatization of public assets",
  "anchor" : "para878"
} ]