[ {
  "text" : "Medical Assistance in Dying Statute Law Amendment Act, 2017 / Loi de 2017 modifiant des lois en ce qui concerne l’aide médicale à mourir",
  "anchor" : "para240"
}, {
  "text" : "Aggregate Resources and Mining Modernization Act, 2017 / Loi de 2017 sur la modernisation des secteurs des ressources en agrégats et des mines",
  "anchor" : "para409"
}, {
  "text" : "Probation and parole services",
  "anchor" : "para478"
}, {
  "text" : "Government accountability",
  "anchor" : "para516"
}, {
  "text" : "Privatization of public assets",
  "anchor" : "para546"
}, {
  "text" : "Hydro rates",
  "anchor" : "para565"
}, {
  "text" : "Lobbyists",
  "anchor" : "para601"
}, {
  "text" : "Privatization of public assets",
  "anchor" : "para619"
}, {
  "text" : "Infrastructure program funding",
  "anchor" : "para645"
}, {
  "text" : "Hydro rates",
  "anchor" : "para659"
}, {
  "text" : "Affordable housing",
  "anchor" : "para692"
}, {
  "text" : "Nurses",
  "anchor" : "para701"
}, {
  "text" : "Labour unions",
  "anchor" : "para715"
}, {
  "text" : "Services for the developmentally disabled",
  "anchor" : "para731"
}, {
  "text" : "Post-traumatic stress disorder",
  "anchor" : "para754"
}, {
  "text" : "Public transit",
  "anchor" : "para766"
}, {
  "text" : "Visitors",
  "anchor" : "para786"
}, {
  "text" : "Medical Assistance in Dying Statute Law Amendment Act, 2017 / Loi de 2017 modifiant des lois en ce qui concerne l’aide médicale à mourir",
  "anchor" : "para802"
}, {
  "text" : "Aggregate Resources and Mining Modernization Act, 2017 / Loi de 2017 sur la modernisation des secteurs des ressources en agrégats et des mines",
  "anchor" : "para1005"
}, {
  "text" : "Royal visit",
  "anchor" : "para1219"
}, {
  "text" : "Myalgic encephalomyelitis",
  "anchor" : "para1224"
}, {
  "text" : "Cootes to Escarpment EcoPark System",
  "anchor" : "para1230"
}, {
  "text" : "Ontario Provincial Police",
  "anchor" : "para1236"
}, {
  "text" : "Community Living Ontario",
  "anchor" : "para1246"
}, {
  "text" : "Myalgic encephalomyelitis",
  "anchor" : "para1251"
}, {
  "text" : "Police services",
  "anchor" : "para1259"
}, {
  "text" : "Indigenous education",
  "anchor" : "para1267"
}, {
  "text" : "Myalgic encephalomyelitis",
  "anchor" : "para1272"
}, {
  "text" : "Standing Committee on Government Agencies",
  "anchor" : "para1278"
}, {
  "text" : "Standing Committee on General Government",
  "anchor" : "para1281"
}, {
  "text" : "South Asian Heritage Month",
  "anchor" : "para1290"
}, {
  "text" : "Jewish Heritage Month",
  "anchor" : "para1304"
}, {
  "text" : "South Asian Heritage Month",
  "anchor" : "para1314"
}, {
  "text" : "Jewish Heritage Month",
  "anchor" : "para1320"
}, {
  "text" : "Jewish Heritage Month",
  "anchor" : "para1340"
}, {
  "text" : "South Asian Heritage Month",
  "anchor" : "para1352"
}, {
  "text" : "Committee sittings",
  "anchor" : "para1362"
}, {
  "text" : "Lyme disease",
  "anchor" : "para1375"
}, {
  "text" : "Provincial truth and reconciliation day",
  "anchor" : "para1382"
}, {
  "text" : "GO Transit",
  "anchor" : "para1395"
}, {
  "text" : "Protection of people with disabilities",
  "anchor" : "para1403"
}, {
  "text" : "Privatization of public assets",
  "anchor" : "para1414"
}, {
  "text" : "Water fluoridation",
  "anchor" : "para1423"
}, {
  "text" : "Long-term care",
  "anchor" : "para1432"
}, {
  "text" : "Veterans",
  "anchor" : "para1442"
}, {
  "text" : "Medical assistance in dying",
  "anchor" : "para1455"
}, {
  "text" : "Government services",
  "anchor" : "para1465"
}, {
  "text" : "Nanjing Massacre",
  "anchor" : "para1481"
}, {
  "text" : "Health care funding",
  "anchor" : "para1492"
}, {
  "text" : "Government accountability / Responsabilité gouvernementale",
  "anchor" : "para1502"
}, {
  "text" : "Government spending",
  "anchor" : "para1884"
} ]