[ {
  "text" : "Accident in Humboldt, Saskatchewan",
  "anchor" : "para242"
}, {
  "text" : "Executive compensation",
  "anchor" : "para249"
}, {
  "text" : "Provincial debt",
  "anchor" : "para281"
}, {
  "text" : "Dental care",
  "anchor" : "para319"
}, {
  "text" : "Dental care",
  "anchor" : "para346"
}, {
  "text" : "Teachers’ collective bargaining",
  "anchor" : "para367"
}, {
  "text" : "Hospital funding",
  "anchor" : "para386"
}, {
  "text" : "Public libraries",
  "anchor" : "para400"
}, {
  "text" : "Member’s comments",
  "anchor" : "para415"
}, {
  "text" : "Dental care",
  "anchor" : "para437"
}, {
  "text" : "Broadband infrastructure",
  "anchor" : "para455"
}, {
  "text" : "Fire safety",
  "anchor" : "para470"
}, {
  "text" : "Environmental protection",
  "anchor" : "para483"
}, {
  "text" : "Indigenous children and youth",
  "anchor" : "para494"
}, {
  "text" : "Hospital funding",
  "anchor" : "para515"
}, {
  "text" : "Consumer protection",
  "anchor" : "para533"
}, {
  "text" : "Notices of dissatisfaction",
  "anchor" : "para539"
}, {
  "text" : "Speaker’s birthday",
  "anchor" : "para542"
}, {
  "text" : "Hockey",
  "anchor" : "para550"
}, {
  "text" : "Leading Women, Leading Girls, Building Communities",
  "anchor" : "para555"
}, {
  "text" : "Battle of Vimy Ridge",
  "anchor" : "para562"
}, {
  "text" : "Rick Lund",
  "anchor" : "para570"
}, {
  "text" : "Accident in Humboldt, Saskatchewan",
  "anchor" : "para575"
}, {
  "text" : "Oncology Nursing Day",
  "anchor" : "para581"
}, {
  "text" : "Organ and tissue donation",
  "anchor" : "para588"
}, {
  "text" : "Ontario budget",
  "anchor" : "para594"
}, {
  "text" : "Battle of Vimy Ridge",
  "anchor" : "para599"
}, {
  "text" : "Use of prop in the House",
  "anchor" : "para610"
}, {
  "text" : "Battle of Vimy Ridge",
  "anchor" : "para613"
}, {
  "text" : "Nanjing Massacre Commemorative Day Act, 2018 / Loi de 2018 sur le Jour commémoratif du massacre de Nanjing",
  "anchor" : "para621"
}, {
  "text" : "Fish and wildlife management",
  "anchor" : "para630"
}, {
  "text" : "Mental health services",
  "anchor" : "para641"
}, {
  "text" : "Health care funding",
  "anchor" : "para655"
}, {
  "text" : "Bombardier lands",
  "anchor" : "para667"
}, {
  "text" : "Ontario Drug Benefit Program",
  "anchor" : "para677"
}, {
  "text" : "Mental health services",
  "anchor" : "para684"
}, {
  "text" : "Correctional services",
  "anchor" : "para696"
}, {
  "text" : "Animal protection",
  "anchor" : "para707"
}, {
  "text" : "Accident benefits",
  "anchor" : "para719"
}, {
  "text" : "Injured workers",
  "anchor" : "para726"
}, {
  "text" : "Government services",
  "anchor" : "para737"
}, {
  "text" : "Pay Transparency Act, 2018 / Loi de 2018 sur la transparence salariale",
  "anchor" : "para748"
}, {
  "text" : "Correctional Services Transformation Act, 2018 / Loi de 2018 sur la transformation des services correctionnels",
  "anchor" : "para1042"
} ]